{"text": " Yn ystod y ffwrdd, y ddau ariannau a'r cwpanau yma, mae'n rhaid i ni ddod o hyd i'r ddau ariannau. Fe wnaethon ni ddod o hyd i'r ddau ariannau a'r cwpanau yma. Mae'n rhaid i ni ddod o hyd i'r ddau ariannau a'r cwpanau yma. Fe wnaethon ni ddod o hyd i'r ddau ariannau a'r cwpanau yma. Fe wnaethon ni ddod o hyd i'r ddau ariannau a'r cwpanau yma. Fe wnaethon ni ddod o hyd i'r ddau ariannau a'r cwpanau yma. Fe wnaethon ni ddod o hyd i'r ddau ariannau a'r cwpanau yma. Fe wnaethon ni ddod o hyd i'r ddau ariannau a'r cwpanau yma.", "segments": [{"id": 0, "seek": 0, "start": 0.0, "end": 7.0, "text": " Yn ystod y ffwrdd, y ddau ariannau a'r cwpanau yma, mae'n rhaid i ni ddod o hyd i'r ddau ariannau.", "tokens": [398, 77, 288, 372, 378, 288, 283, 69, 7449, 24810, 11, 288, 274, 67, 1459, 257, 470, 969, 1459, 257, 6, 81, 269, 86, 6040, 1459, 288, 1696, 11, 43783, 6, 77, 367, 1641, 327, 741, 3867, 274, 67, 378, 277, 5796, 741, 6, 81, 274, 67, 1459, 257, 470, 969, 1459, 13], "temperature": 0.4, "avg_logprob": -0.9489482092478919, "compression_ratio": 2.1553398058252426, "no_speech_prob": 0.8299292922019958}, {"id": 1, "seek": 0, "start": 8.0, "end": 13.0, "text": " Fe wnaethon ni ddod o hyd i'r ddau ariannau a'r cwpanau yma.", "tokens": [3697, 261, 629, 3293, 266, 3867, 274, 67, 378, 277, 5796, 741, 6, 81, 274, 67, 1459, 257, 470, 969, 1459, 257, 6, 81, 269, 86, 6040, 1459, 288, 1696, 13], "temperature": 0.4, "avg_logprob": -0.9489482092478919, "compression_ratio": 2.1553398058252426, "no_speech_prob": 0.8299292922019958}, {"id": 2, "seek": 0, "start": 13.0, "end": 18.0, "text": " Mae'n rhaid i ni ddod o hyd i'r ddau ariannau a'r cwpanau yma.", "tokens": [376, 8346, 6, 77, 367, 1641, 327, 741, 3867, 274, 67, 378, 277, 5796, 741, 6, 81, 274, 67, 1459, 257, 470, 969, 1459, 257, 6, 81, 269, 86, 6040, 1459, 288, 1696, 13], "temperature": 0.4, "avg_logprob": -0.9489482092478919, "compression_ratio": 2.1553398058252426, "no_speech_prob": 0.8299292922019958}, {"id": 3, "seek": 1800, "start": 18.0, "end": 31.0, "text": " Fe wnaethon ni ddod o hyd i'r ddau ariannau a'r cwpanau yma.", "tokens": [3697, 261, 629, 3293, 266, 3867, 274, 67, 378, 277, 5796, 741, 6, 81, 274, 67, 1459, 257, 470, 969, 1459, 257, 6, 81, 269, 86, 6040, 1459, 288, 1696, 13], "temperature": 0.0, "avg_logprob": -0.24175512089448817, "compression_ratio": 1.8615384615384616, "no_speech_prob": 0.057119015604257584}, {"id": 4, "seek": 1800, "start": 31.0, "end": 41.0, "text": " Fe wnaethon ni ddod o hyd i'r ddau ariannau a'r cwpanau yma.", "tokens": [3697, 261, 629, 3293, 266, 3867, 274, 67, 378, 277, 5796, 741, 6, 81, 274, 67, 1459, 257, 470, 969, 1459, 257, 6, 81, 269, 86, 6040, 1459, 288, 1696, 13], "temperature": 0.0, "avg_logprob": -0.24175512089448817, "compression_ratio": 1.8615384615384616, "no_speech_prob": 0.057119015604257584}, {"id": 5, "seek": 4100, "start": 41.0, "end": 51.0, "text": " Fe wnaethon ni ddod o hyd i'r ddau ariannau a'r cwpanau yma.", "tokens": [50364, 3697, 261, 629, 3293, 266, 3867, 274, 67, 378, 277, 5796, 741, 6, 81, 274, 67, 1459, 257, 470, 969, 1459, 257, 6, 81, 269, 86, 6040, 1459, 288, 1696, 13, 50864], "temperature": 0.0, "avg_logprob": -0.19657379038193645, "compression_ratio": 0.9836065573770492, "no_speech_prob": 0.001251125824637711}, {"id": 6, "seek": 7100, "start": 71.0, "end": 81.0, "text": " Fe wnaethon ni ddod o hyd i'r ddau ariannau a'r cwpanau yma.", "tokens": [3697, 261, 629, 3293, 266, 3867, 274, 67, 378, 277, 5796, 741, 6, 81, 274, 67, 1459, 257, 470, 969, 1459, 257, 6, 81, 269, 86, 6040, 1459, 288, 1696, 13], "temperature": 0.0, "avg_logprob": -0.14671809533063104, "compression_ratio": 1.8615384615384616, "no_speech_prob": 0.8469709753990173}, {"id": 7, "seek": 7100, "start": 81.0, "end": 91.0, "text": " Fe wnaethon ni ddod o hyd i'r ddau ariannau a'r cwpanau yma.", "tokens": [3697, 261, 629, 3293, 266, 3867, 274, 67, 378, 277, 5796, 741, 6, 81, 274, 67, 1459, 257, 470, 969, 1459, 257, 6, 81, 269, 86, 6040, 1459, 288, 1696, 13], "temperature": 0.0, "avg_logprob": -0.14671809533063104, "compression_ratio": 1.8615384615384616, "no_speech_prob": 0.8469709753990173}], "language": "cy"}